vfunctions_sdk/NSM.py
vfunctions_sdk/__init__.py
vfunctions_sdk/connection.py
vfunctions_sdk/publish.py
vfunctions_sdk/vFunction.py
vfunctions_sdk-0.0.7.dist-info/LICENSE
vfunctions_sdk-0.0.7.dist-info/METADATA
vfunctions_sdk-0.0.7.dist-info/WHEEL
vfunctions_sdk-0.0.7.dist-info/top_level.txt
vfunctions_sdk-0.0.7.dist-info/RECORD
