Metadata-Version: 2.1
Name: vfunctions-sdk
Version: 0.0.7
Summary: A package to manage development inside nitro enclaves.
Home-page: https://github.com/verifiably/vfunctions-sdk
Author: Verifiably
Author-email: contact@verifiably.com
License: UNKNOWN
Keywords: python,nitro-enclave,security
Platform: UNKNOWN
Classifier: Intended Audience :: Developers
Classifier: Programming Language :: Python :: 3
Classifier: Operating System :: OS Independent
Requires-Python: >=3.8
Requires-Dist: aws-nsm-interface-verifiably
Requires-Dist: boto3
Requires-Dist: cbor2 (==5.2.0)
Requires-Dist: cryptography (==3.2.1)
Requires-Dist: pycryptodome (==3.9.9)
Requires-Dist: websocket-client
